sdvrp_py-0.1.1.dist-info/METADATA
sdvrp_py-0.1.1.dist-info/WHEEL
sdvrp_py/__init__.py
sdvrp_py/_core.abi3.so
sdvrp_py/_core.pyi
sdvrp_py/py.typed
sdvrp_py/rstypes.py
sdvrp_py-0.1.1.dist-info/RECORD
