Metadata-Version: 2.4
Name: sdvrp-py
Version: 0.1.1
Summary: Python binding of Alkaid-SDVRP: An Efficient Open-Source Solver for the Vehicle Routing Problem with Split Deliveries.
Author-email: HellOwhatAs <xjq701229@outlook.com>
Requires-Python: >=3.9
